CHANGES.rst
MANIFEST.in
README.rst
how-to-start-mongodb.txt
old_sentry.txt
requirements.txt
setup.cfg
setup.py
requirements/docs.txt
requirements/pypy.txt
requirements/python2.txt
requirements/test_support.txt
requirements/testing.txt
yith_library_server.egg-info/PKG-INFO
yith_library_server.egg-info/SOURCES.txt
yith_library_server.egg-info/dependency_links.txt
yith_library_server.egg-info/entry_points.txt
yith_library_server.egg-info/not-zip-safe
yith_library_server.egg-info/pbr.json
yith_library_server.egg-info/requires.txt
yith_library_server.egg-info/top_level.txt
yithlibraryserver/__init__.py
yithlibraryserver/assets.py
yithlibraryserver/compat.py
yithlibraryserver/config.py
yithlibraryserver/cors.py
yithlibraryserver/email.py
yithlibraryserver/errors.py
yithlibraryserver/i18n.py
yithlibraryserver/jsonrenderer.py
yithlibraryserver/locale.py
yithlibraryserver/schemas.py
yithlibraryserver/security.py
yithlibraryserver/sna_callbacks.py
yithlibraryserver/subscribers.py
yithlibraryserver/testing.py
yithlibraryserver/utils.py
yithlibraryserver/views.py
yithlibraryserver/backups/__init__.py
yithlibraryserver/backups/email.py
yithlibraryserver/backups/utils.py
yithlibraryserver/backups/views.py
yithlibraryserver/backups/templates/backups_index.pt
yithlibraryserver/backups/templates/email_passwords.pt
yithlibraryserver/backups/templates/email_passwords.txt
yithlibraryserver/backups/tests/__init__.py
yithlibraryserver/backups/tests/test_email.py
yithlibraryserver/backups/tests/test_utils.py
yithlibraryserver/backups/tests/test_views.py
yithlibraryserver/config-templates/development.ini
yithlibraryserver/config-templates/production.ini
yithlibraryserver/contributions/__init__.py
yithlibraryserver/contributions/email.py
yithlibraryserver/contributions/models.py
yithlibraryserver/contributions/paypal.py
yithlibraryserver/contributions/views.py
yithlibraryserver/contributions/templates/contributions_confirm.pt
yithlibraryserver/contributions/templates/contributions_index.pt
yithlibraryserver/contributions/templates/email_admin_notification.pt
yithlibraryserver/contributions/templates/email_admin_notification.txt
yithlibraryserver/contributions/templates/email_thankyou.pt
yithlibraryserver/contributions/templates/email_thankyou.txt
yithlibraryserver/contributions/tests/__init__.py
